AUTHORS.rst
CHANGELOG.rst
MANIFEST.in
README.rst
setup.py
shaunsephton/__init__.py
shaunsephton.recipe.uwsgi.egg-info/PKG-INFO
shaunsephton.recipe.uwsgi.egg-info/SOURCES.txt
shaunsephton.recipe.uwsgi.egg-info/dependency_links.txt
shaunsephton.recipe.uwsgi.egg-info/entry_points.txt
shaunsephton.recipe.uwsgi.egg-info/not-zip-safe
shaunsephton.recipe.uwsgi.egg-info/requires.txt
shaunsephton.recipe.uwsgi.egg-info/top_level.txt
shaunsephton/recipe/__init__.py
shaunsephton/recipe/uwsgi.py