Metadata-Version: 1.0
Name: shaunsephton.recipe.uwsgi
Version: 0.0.9
Summary: Buildout recipe downloading, compiling and configuring uWSGI.
Home-page: http://github.com/shaunsephton/shaunsephton.recipe.uwsgi
Author: Shaun Sephton
Author-email: shaunsephton@gmail.com
License: BSD
Platform: UNKNOWN
Classifier: Programming Language :: Python
Classifier: License :: OSI Approved :: BSD License
Classifier: Development Status :: 4 - Beta
Classifier: Operating System :: OS Independent
Classifier: Framework :: Buildout
Classifier: Intended Audience :: Developers
Classifier: Topic :: Internet :: WWW/HTTP :: Dynamic Content
